omega_tslib/exploratory_analysis.py
omega_tslib/services/__init__.py
omega_tslib/services/main.py
omega_tslib/services/services_database.py
omega_tslib/services/services_export_granularity.py
omega_tslib/services/services_reference.yml
omega_tslib/services/sf_connection.py
omega_tslib/services/theme.py
omega_tslib/services/timeseries.py
omega_tslib/utils/__init__.py
omega_tslib/utils/utils_logger.py
omega_tslib/utils/utils_ref.py
omega_tslib-0.0.3.dist-info/METADATA
omega_tslib-0.0.3.dist-info/WHEEL
omega_tslib-0.0.3.dist-info/RECORD
