Metadata-Version: 2.1
Name: omega-tslib
Version: 0.0.3
Summary: An intuitive Python library for time series analysis and forecasting models. Simplify the complexity of time series tasks with comprehensive preprocessing, exploratory analysis, and accurate forecasting model building.
Home-page: https://github.com/omega-energia-analytics/comercializacao-ml
Author: Diego Neri
Author-email: diego.neri@omegaenergia.com.br
Requires-Python: >=3.8,<3.11
Classifier: Programming Language :: Python :: 3
Classifier: Programming Language :: Python :: 3.8
Classifier: Programming Language :: Python :: 3.9
Classifier: Programming Language :: Python :: 3.10
Requires-Dist: matplotlib (>=3.7.2,<4.0.0)
Requires-Dist: numpy (==1.23.3)
Requires-Dist: pandas (>=1.5.0,<2.0.0)
Requires-Dist: plotly (>=5.16.1,<6.0.0)
Requires-Dist: python-dotenv (>=0.19.1,<0.20.0)
Requires-Dist: pyyaml (>=6.0.1,<7.0.0)
Requires-Dist: scikit-learn (>=1.3.0,<2.0.0)
Requires-Dist: statsmodels (>=0.14.0,<0.15.0)
Project-URL: Repository, https://github.com/omega-energia-analytics/comercializacao-ml
